Metadata-Version: 1.1
Name: sound-weighting-filters
Version: 0.9.0
Summary: IIR coefficients for A,B,C and ITU_R_468 weighting filters
Home-page: https://github.com/berndporr/sound_weighting_filters
Author: Bernd Porr
Author-email: mail@berndporr.me.uk
License: MIT
Platform: UNKNOWN
Classifier: Intended Audience :: Developers
Classifier: Operating System :: OS Independent
Classifier: Programming Language :: Python :: 3
